BinaryTreeSearch/BinaryConverter.py
BinaryTreeSearch/BinaryTreeClass.py
BinaryTreeSearch/MergeSortClass.py
BinaryTreeSearch/__init__.py
BinaryTreeSearcher-1.0.5.dist-info/LICENSE.txt
BinaryTreeSearcher-1.0.5.dist-info/METADATA
BinaryTreeSearcher-1.0.5.dist-info/WHEEL
BinaryTreeSearcher-1.0.5.dist-info/top_level.txt
BinaryTreeSearcher-1.0.5.dist-info/RECORD
