Metadata-Version: 2.1
Name: BinaryTreeSearcher
Version: 1.0.5
Summary: A simple binary tree search library
Home-page: https://github.com/DR-FREKE/BinaryTreeSearch
Author: Solomon Ndifereke Aniefiok
Author-email: solomonndi96@gmail.com
License: UNKNOWN
Platform: UNKNOWN
Classifier: Programming Language :: Python :: 3
Classifier: License :: OSI Approved :: MIT License
Classifier: Operating System :: OS Independent
Requires-Python: >=3.6
